{"errors":[],"warnings":["./src/components/TaggedList/index.jsx 20:33-49\n\"export 'CONTENT_PER_PAGE' was not found in 'constants'","./src/components/Common/Pagination/index.jsx 22:52-68\n\"export 'CONTENT_PER_PAGE' was not found in 'constants'","./src/components/List/index.jsx 19:58-74\n\"export 'CONTENT_PER_PAGE' was not found in 'constants'","./src/components/List/index.jsx 19:33-49\n\"export 'CONTENT_PER_PAGE' was not found in 'constants'","./src/components/TaggedList/index.jsx 20:58-74\n\"export 'CONTENT_PER_PAGE' was not found in 'constants'","./src/components/CategorizedList/index.jsx 20:58-74\n\"export 'CONTENT_PER_PAGE' was not found in 'constants'","./src/components/CategorizedList/index.jsx 20:33-49\n\"export 'CONTENT_PER_PAGE' was not found in 'constants'","./src/components/Common/Pagination/index.jsx 29:41-56\n\"export 'PAGE_PER_SCREEN' was not found in 'constants'","./src/components/Common/Pagination/index.jsx 26:34-49\n\"export 'PAGE_PER_SCREEN' was not found in 'constants'","./src/components/layout.jsx 22:73-82\n\"export 'PORTFOLIO' was not found in 'constants'","./src/components/layout.jsx 39:101-105\n\"export 'POST' was not found in 'constants'","./src/components/layout.jsx 39:86-90\n\"export 'POST' was not found in 'constants'","./src/utils/getPosts.js 7:45-49\n\"export 'POST' was not found in 'constants'","./src/utils/getPosts.js 7:35-39\n\"export 'POST' was not found in 'constants'","./src/components/Post/index.jsx 39:18-26\n\"export 'SITE_URL' was not found in 'constants'","./src/resources/test-2/index.md 1:2\nModule parse failed: Assigning to rvalue (1:2)\nYou may need an appropriate loader to handle this file type.\n> ---\n| type: \"portfolio\"\n| title: \"Gatsby Advanced Blog\"","./src/resources/test-4/index.md 1:2\nModule parse failed: Assigning to rvalue (1:2)\nYou may need an appropriate loader to handle this file type.\n> ---\n| type: \"portfolio\"\n| title: \"Gatsby Advanced Blog\"","./src/resources/test-3/index.md 1:2\nModule parse failed: Assigning to rvalue (1:2)\nYou may need an appropriate loader to handle this file type.\n> ---\n| type: \"portfolio\"\n| title: \"Gatsby Advanced Blog\"","./src/resources/test-1/index.md 1:2\nModule parse failed: Assigning to rvalue (1:2)\nYou may need an appropriate loader to handle this file type.\n> ---\n| type: \"portfolio\"\n| title: \"Gatsby Advanced Blog\"","./src/resources/resume/index.md 1:2\nModule parse failed: Assigning to rvalue (1:2)\nYou may need an appropriate loader to handle this file type.\n> ---\n| type: \"resume\"\n| title: \"Resume\""],"namedChunkGroups":{"app":{"chunks":[15,4],"assets":["webpack-runtime-a5bb207ac73fd34f9521.js","webpack-runtime-a5bb207ac73fd34f9521.js.map","app-7e89af63c53d1857478e.js","app-7e89af63c53d1857478e.js.map"],"children":{},"childAssets":{}},"component---node-modules-gatsby-plugin-offline-app-shell-js":{"chunks":[16],"assets":["16-fa38b6f4bb9b377dd57e.js","16-fa38b6f4bb9b377dd57e.js.map"],"children":{},"childAssets":{}},"component---src-templates-post-jsx":{"chunks":[0,1,2,11],"assets":["0-433b60e2eb4cb10a9ab1.js","0-433b60e2eb4cb10a9ab1.js.map","1-91a9a0ae1c1364b764b2.js","1-91a9a0ae1c1364b764b2.js.map","2-b43146230cf9e502ff2d.js","2-b43146230cf9e502ff2d.js.map","component---src-templates-post-jsx-f2f996f1f1e7617804c8.js","component---src-templates-post-jsx-f2f996f1f1e7617804c8.js.map"],"children":{},"childAssets":{}},"component---src-templates-resume-jsx":{"chunks":[0,1,2,12],"assets":["0-433b60e2eb4cb10a9ab1.js","0-433b60e2eb4cb10a9ab1.js.map","1-91a9a0ae1c1364b764b2.js","1-91a9a0ae1c1364b764b2.js.map","2-b43146230cf9e502ff2d.js","2-b43146230cf9e502ff2d.js.map","component---src-templates-resume-jsx-0b3c2d44b0f3e4170136.js","component---src-templates-resume-jsx-0b3c2d44b0f3e4170136.js.map"],"children":{},"childAssets":{}},"component---src-templates-portfolio-jsx":{"chunks":[0,1,2,9],"assets":["0-433b60e2eb4cb10a9ab1.js","0-433b60e2eb4cb10a9ab1.js.map","1-91a9a0ae1c1364b764b2.js","1-91a9a0ae1c1364b764b2.js.map","2-b43146230cf9e502ff2d.js","2-b43146230cf9e502ff2d.js.map","component---src-templates-portfolio-jsx-529c30cdb582b7c4664d.js","component---src-templates-portfolio-jsx-529c30cdb582b7c4664d.js.map"],"children":{},"childAssets":{}},"component---src-templates-portfolios-jsx":{"chunks":[0,1,2,10],"assets":["0-433b60e2eb4cb10a9ab1.js","0-433b60e2eb4cb10a9ab1.js.map","1-91a9a0ae1c1364b764b2.js","1-91a9a0ae1c1364b764b2.js.map","2-b43146230cf9e502ff2d.js","2-b43146230cf9e502ff2d.js.map","component---src-templates-portfolios-jsx-e6f5199131cf8649c9c1.js","component---src-templates-portfolios-jsx-e6f5199131cf8649c9c1.js.map"],"children":{},"childAssets":{}},"component---src-templates-list-jsx":{"chunks":[0,1,2,3,8],"assets":["0-433b60e2eb4cb10a9ab1.js","0-433b60e2eb4cb10a9ab1.js.map","1-91a9a0ae1c1364b764b2.js","1-91a9a0ae1c1364b764b2.js.map","2-b43146230cf9e502ff2d.js","2-b43146230cf9e502ff2d.js.map","3-b0bb40febb1d2106454c.js","3-b0bb40febb1d2106454c.js.map","component---src-templates-list-jsx-6612cbafddce30d15c59.js","component---src-templates-list-jsx-6612cbafddce30d15c59.js.map"],"children":{},"childAssets":{}},"component---src-templates-tagged-list-jsx":{"chunks":[0,1,2,3,13],"assets":["0-433b60e2eb4cb10a9ab1.js","0-433b60e2eb4cb10a9ab1.js.map","1-91a9a0ae1c1364b764b2.js","1-91a9a0ae1c1364b764b2.js.map","2-b43146230cf9e502ff2d.js","2-b43146230cf9e502ff2d.js.map","3-b0bb40febb1d2106454c.js","3-b0bb40febb1d2106454c.js.map","component---src-templates-tagged-list-jsx-f9a5df727e77acbfa911.js","component---src-templates-tagged-list-jsx-f9a5df727e77acbfa911.js.map"],"children":{},"childAssets":{}},"component---src-templates-categorized-list-jsx":{"chunks":[0,1,2,3,7],"assets":["0-433b60e2eb4cb10a9ab1.js","0-433b60e2eb4cb10a9ab1.js.map","1-91a9a0ae1c1364b764b2.js","1-91a9a0ae1c1364b764b2.js.map","2-b43146230cf9e502ff2d.js","2-b43146230cf9e502ff2d.js.map","3-b0bb40febb1d2106454c.js","3-b0bb40febb1d2106454c.js.map","component---src-templates-categorized-list-jsx-fae14f446704dab078f4.js","component---src-templates-categorized-list-jsx-fae14f446704dab078f4.js.map"],"children":{},"childAssets":{}},"component---src-pages-404-jsx":{"chunks":[0,5],"assets":["0-433b60e2eb4cb10a9ab1.js","0-433b60e2eb4cb10a9ab1.js.map","component---src-pages-404-jsx-ac3a6c653095147f28a1.js","component---src-pages-404-jsx-ac3a6c653095147f28a1.js.map"],"children":{},"childAssets":{}},"component---src-pages-index-jsx":{"chunks":[0,1,2,6],"assets":["0-433b60e2eb4cb10a9ab1.js","0-433b60e2eb4cb10a9ab1.js.map","1-91a9a0ae1c1364b764b2.js","1-91a9a0ae1c1364b764b2.js.map","2-b43146230cf9e502ff2d.js","2-b43146230cf9e502ff2d.js.map","component---src-pages-index-jsx-138c513a5fab20b9c79c.js","component---src-pages-index-jsx-138c513a5fab20b9c79c.js.map"],"children":{},"childAssets":{}},"pages-manifest":{"chunks":[14],"assets":["pages-manifest-8532062d5d3758fbae25.js","pages-manifest-8532062d5d3758fbae25.js.map"],"children":{},"childAssets":{}}},"assetsByChunkName":{"app":["webpack-runtime-a5bb207ac73fd34f9521.js","app-7e89af63c53d1857478e.js"],"component---node-modules-gatsby-plugin-offline-app-shell-js":["16-fa38b6f4bb9b377dd57e.js"],"component---src-templates-post-jsx":["0-433b60e2eb4cb10a9ab1.js","1-91a9a0ae1c1364b764b2.js","2-b43146230cf9e502ff2d.js","component---src-templates-post-jsx-f2f996f1f1e7617804c8.js"],"component---src-templates-resume-jsx":["0-433b60e2eb4cb10a9ab1.js","1-91a9a0ae1c1364b764b2.js","2-b43146230cf9e502ff2d.js","component---src-templates-resume-jsx-0b3c2d44b0f3e4170136.js"],"component---src-templates-portfolio-jsx":["0-433b60e2eb4cb10a9ab1.js","1-91a9a0ae1c1364b764b2.js","2-b43146230cf9e502ff2d.js","component---src-templates-portfolio-jsx-529c30cdb582b7c4664d.js"],"component---src-templates-portfolios-jsx":["0-433b60e2eb4cb10a9ab1.js","1-91a9a0ae1c1364b764b2.js","2-b43146230cf9e502ff2d.js","component---src-templates-portfolios-jsx-e6f5199131cf8649c9c1.js"],"component---src-templates-list-jsx":["0-433b60e2eb4cb10a9ab1.js","1-91a9a0ae1c1364b764b2.js","2-b43146230cf9e502ff2d.js","3-b0bb40febb1d2106454c.js","component---src-templates-list-jsx-6612cbafddce30d15c59.js"],"component---src-templates-tagged-list-jsx":["0-433b60e2eb4cb10a9ab1.js","1-91a9a0ae1c1364b764b2.js","2-b43146230cf9e502ff2d.js","3-b0bb40febb1d2106454c.js","component---src-templates-tagged-list-jsx-f9a5df727e77acbfa911.js"],"component---src-templates-categorized-list-jsx":["0-433b60e2eb4cb10a9ab1.js","1-91a9a0ae1c1364b764b2.js","2-b43146230cf9e502ff2d.js","3-b0bb40febb1d2106454c.js","component---src-templates-categorized-list-jsx-fae14f446704dab078f4.js"],"component---src-pages-404-jsx":["0-433b60e2eb4cb10a9ab1.js","component---src-pages-404-jsx-ac3a6c653095147f28a1.js"],"component---src-pages-index-jsx":["0-433b60e2eb4cb10a9ab1.js","1-91a9a0ae1c1364b764b2.js","2-b43146230cf9e502ff2d.js","component---src-pages-index-jsx-138c513a5fab20b9c79c.js"],"pages-manifest":["pages-manifest-8532062d5d3758fbae25.js"]}}